TongwangCaifuZiyouZhiLuJingxiBiji/README.md
TongwangCaifuZiyouZhiLuJingxiBiji/__init__.py
TongwangCaifuZiyouZhiLuJingxiBiji/__main__.py
TongwangCaifuZiyouZhiLuJingxiBiji/file.epub
TongwangCaifuZiyouZhiLuJingxiBiji/index.html
TongwangCaifuZiyouZhiLuJingxiBiji/css/__init__.py
TongwangCaifuZiyouZhiLuJingxiBiji/css/annotations.css
TongwangCaifuZiyouZhiLuJingxiBiji/css/main.css
TongwangCaifuZiyouZhiLuJingxiBiji/css/normalize.css
TongwangCaifuZiyouZhiLuJingxiBiji/css/popup.css
TongwangCaifuZiyouZhiLuJingxiBiji/font/__init__.py
TongwangCaifuZiyouZhiLuJingxiBiji/font/fontello.eot
TongwangCaifuZiyouZhiLuJingxiBiji/font/fontello.svg
TongwangCaifuZiyouZhiLuJingxiBiji/font/fontello.ttf
TongwangCaifuZiyouZhiLuJingxiBiji/font/fontello.woff
TongwangCaifuZiyouZhiLuJingxiBiji/img/__init__.py
TongwangCaifuZiyouZhiLuJingxiBiji/img/annotator-glyph-sprite.png
TongwangCaifuZiyouZhiLuJingxiBiji/img/annotator-icon-sprite.png
TongwangCaifuZiyouZhiLuJingxiBiji/img/apple-touch-icon.png
TongwangCaifuZiyouZhiLuJingxiBiji/img/cancelfullscreen.png
TongwangCaifuZiyouZhiLuJingxiBiji/img/close.png
TongwangCaifuZiyouZhiLuJingxiBiji/img/fullscreen.png
TongwangCaifuZiyouZhiLuJingxiBiji/img/loader.gif
TongwangCaifuZiyouZhiLuJingxiBiji/img/menu-icon.png
TongwangCaifuZiyouZhiLuJingxiBiji/img/save.png
TongwangCaifuZiyouZhiLuJingxiBiji/img/saved.png
TongwangCaifuZiyouZhiLuJingxiBiji/img/settings-s.png
TongwangCaifuZiyouZhiLuJingxiBiji/img/settings.png
TongwangCaifuZiyouZhiLuJingxiBiji/img/star.png
TongwangCaifuZiyouZhiLuJingxiBiji/js/__init__.py
TongwangCaifuZiyouZhiLuJingxiBiji/js/epub.js
TongwangCaifuZiyouZhiLuJingxiBiji/js/epub.min.js
TongwangCaifuZiyouZhiLuJingxiBiji/js/epub.min.map
TongwangCaifuZiyouZhiLuJingxiBiji/js/hooks.min.js
TongwangCaifuZiyouZhiLuJingxiBiji/js/hooks.min.map
TongwangCaifuZiyouZhiLuJingxiBiji/js/reader.js
TongwangCaifuZiyouZhiLuJingxiBiji/js/reader.js.map
TongwangCaifuZiyouZhiLuJingxiBiji/js/reader.min.js
TongwangCaifuZiyouZhiLuJingxiBiji/js/reader.min.map
tongwang_caifu_ziyou_zhi_lu_jingxi_biji-2024.3.5.0.dist-info/METADATA
tongwang_caifu_ziyou_zhi_lu_jingxi_biji-2024.3.5.0.dist-info/WHEEL
tongwang_caifu_ziyou_zhi_lu_jingxi_biji-2024.3.5.0.dist-info/entry_points.txt
tongwang_caifu_ziyou_zhi_lu_jingxi_biji-2024.3.5.0.dist-info/top_level.txt
tongwang_caifu_ziyou_zhi_lu_jingxi_biji-2024.3.5.0.dist-info/RECORD
